convolutional_variational_autoencoder_pytorch/__init__.py
convolutional_variational_autoencoder_pytorch/module.py
convolutional_variational_autoencoder_pytorch-0.1.1.dist-info/licenses/LICENSE
convolutional_variational_autoencoder_pytorch-0.1.1.dist-info/METADATA
convolutional_variational_autoencoder_pytorch-0.1.1.dist-info/WHEEL
convolutional_variational_autoencoder_pytorch-0.1.1.dist-info/top_level.txt
convolutional_variational_autoencoder_pytorch-0.1.1.dist-info/RECORD
