Metadata-Version: 2.4
Name: convolutional-variational-autoencoder-pytorch
Version: 0.1.1
Summary: A package to simplify the implementing a variationsl-autoencoder model.
Author-email: Mehran Bazrafkan <mhrn.bzrafkn.dev@gmail.com>
License-Expression: MIT
Keywords: variational autoencoder,pytorch,ml,deep learning
Classifier: Programming Language :: Python :: 3
Classifier: Operating System :: OS Independent
Requires-Python: >=3.10
License-File: LICENSE
Dynamic: license-file
